{"region":"f72ed7e4-cb39-42ef-a866-a8e06bf3a89d","model":{"(!COMMIT_ON_CLOSE || !USE_COMPOUND_FILE)":266383.3333333333,"(COMMIT_ON_CLOSE && USE_COMPOUND_FILE)":0.0},"modelToMin":{"(!COMMIT_ON_CLOSE || !USE_COMPOUND_FILE)":0.0,"(COMMIT_ON_CLOSE && USE_COMPOUND_FILE)":0.0},"modelToMax":{"(!COMMIT_ON_CLOSE || !USE_COMPOUND_FILE)":1078000.0,"(COMMIT_ON_CLOSE && USE_COMPOUND_FILE)":0.0},"modelToDiff":{"(!COMMIT_ON_CLOSE || !USE_COMPOUND_FILE)":1078000.0,"(COMMIT_ON_CLOSE && USE_COMPOUND_FILE)":0.0},"modelToSampleVariance":{"(!COMMIT_ON_CLOSE || !USE_COMPOUND_FILE)":2.3225433060606058E11,"(COMMIT_ON_CLOSE && USE_COMPOUND_FILE)":0.0},"modelToConfidenceInterval":{"(!COMMIT_ON_CLOSE || !USE_COMPOUND_FILE)":[0.0,572585.6002821474],"(COMMIT_ON_CLOSE && USE_COMPOUND_FILE)":[0.0,0.0]},"modelToPerfHumanReadable":{"(!COMMIT_ON_CLOSE || !USE_COMPOUND_FILE)":"0.0002664","(COMMIT_ON_CLOSE && USE_COMPOUND_FILE)":"0.0000000"},"modelToMinHumanReadable":{"(!COMMIT_ON_CLOSE || !USE_COMPOUND_FILE)":"0.0000000","(COMMIT_ON_CLOSE && USE_COMPOUND_FILE)":"0.0000000"},"modelToMaxHumanReadable":{"(!COMMIT_ON_CLOSE || !USE_COMPOUND_FILE)":"0.0010780","(COMMIT_ON_CLOSE && USE_COMPOUND_FILE)":"0.0000000"},"modelToDiffHumanReadable":{"(!COMMIT_ON_CLOSE || !USE_COMPOUND_FILE)":"0.0010780","(COMMIT_ON_CLOSE && USE_COMPOUND_FILE)":"0.0000000"},"modelToSampleVarianceHumanReadble":{"(!COMMIT_ON_CLOSE || !USE_COMPOUND_FILE)":"0.0000002","(COMMIT_ON_CLOSE && USE_COMPOUND_FILE)":"0.0000000"},"modelToConfidenceIntervalHumanReadable":{"(!COMMIT_ON_CLOSE || !USE_COMPOUND_FILE)":["0.0000000","0.0005726"],"(COMMIT_ON_CLOSE && USE_COMPOUND_FILE)":["0.0000000","0.0000000"]}}