[
  {
    "region": {
      "regionID": "d566f2d3-c694-426d-b1d4-eb39b175f97a",
      "startTime": -1,
      "endTime": -1,
      "duration": -1,
      "regionPackage": "edu.cmu.cs.mvelezce.analysis",
      "regionClass": "Example1",
      "regionMethod": "main([Ljava/lang/String;)V",
      "startRegionIndex": 1,
      "startBlockID": "",
      "endBlocksIDs": [],
      "startMethodBlock": null,
      "endMethodBlocks": []
    },
    "info": {
      "context": [
        [],
        [
          "A"
        ],
        [
          "B"
        ],
        [
          "A",
          "B"
        ]
      ],
      "decisionBranchTable": {
        "options": [
          "A",
          "B"
        ],
        "table": {
          "{A=false, B=true}": {
            "thenCount": 1,
            "elseCount": 0
          },
          "{A=true, B=false}": {
            "thenCount": 0,
            "elseCount": 1
          },
          "{A=false, B=false}": {
            "thenCount": 1,
            "elseCount": 0
          },
          "{A=true, B=true}": {
            "thenCount": 0,
            "elseCount": 1
          }
        }
      }
    }
  },
  {
    "region": {
      "regionID": "08c32107-0e1a-428c-a340-9e2b3b529af4",
      "startTime": -1,
      "endTime": -1,
      "duration": -1,
      "regionPackage": "edu.cmu.cs.mvelezce.analysis",
      "regionClass": "Example1",
      "regionMethod": "main([Ljava/lang/String;)V",
      "startRegionIndex": 2,
      "startBlockID": "",
      "endBlocksIDs": [],
      "startMethodBlock": null,
      "endMethodBlocks": []
    },
    "info": {
      "context": [
        [],
        [
          "A"
        ],
        [
          "B"
        ],
        [
          "A",
          "B"
        ]
      ],
      "decisionBranchTable": {
        "options": [
          "A",
          "B"
        ],
        "table": {
          "{A=false, B=true}": {
            "thenCount": 1,
            "elseCount": 0
          },
          "{A=true, B=false}": {
            "thenCount": 0,
            "elseCount": 1
          },
          "{A=false, B=false}": {
            "thenCount": 1,
            "elseCount": 0
          },
          "{A=true, B=true}": {
            "thenCount": 0,
            "elseCount": 1
          }
        }
      }
    }
  },
  {
    "region": {
      "regionID": "8d3ded6f-ba71-4a4a-93c9-ca7c949ca3b1",
      "startTime": -1,
      "endTime": -1,
      "duration": -1,
      "regionPackage": "edu.cmu.cs.mvelezce.analysis",
      "regionClass": "Example1",
      "regionMethod": "main([Ljava/lang/String;)V",
      "startRegionIndex": 3,
      "startBlockID": "",
      "endBlocksIDs": [],
      "startMethodBlock": null,
      "endMethodBlocks": []
    },
    "info": {
      "context": [
        [],
        [
          "B"
        ]
      ],
      "decisionBranchTable": {
        "options": [
          "A",
          "B"
        ],
        "table": {
          "{A=false, B=true}": {
            "thenCount": 1,
            "elseCount": 0
          },
          "{A=false, B=false}": {
            "thenCount": 0,
            "elseCount": 1
          }
        }
      }
    }
  }
]