[{"region":{"regionID":"d2e2818a-a423-46fe-b65e-1ece12ffb27f","startTime":-1,"endTime":-1,"duration":-1,"regionPackage":"edu.cmu.cs.mvelezce.analysis","regionClass":"ForExample","regionMethod":"main([Ljava/lang/String;)V","startRegionIndex":7,"startBlockID":"","endBlocksIDs":[],"startMethodBlock":null,"endMethodBlocks":[]},"info":{"stackTracesToContexts":{"[]":{"context":[["A","B"],["A","B","C"],["A","B","D"],["A","B","E"],["A","B","C","D"],["A","B","C","E"],["A","B","D","E"],["A","B","C","D","E"]]}},"stackTracesToDecisionBranchTables":{"[]":{"options":["A","B","C","D","E"],"table":{"{A=true, B=true, C=false, D=false, E=false}":{"thenCount":1,"elseCount":0},"{A=true, B=true, C=true, D=true, E=false}":{"thenCount":1,"elseCount":0},"{A=true, B=true, C=true, D=false, E=true}":{"thenCount":1,"elseCount":0},"{A=true, B=true, C=false, D=true, E=true}":{"thenCount":1,"elseCount":0},"{A=true, B=true, C=true, D=false, E=false}":{"thenCount":1,"elseCount":0},"{A=true, B=true, C=false, D=true, E=false}":{"thenCount":1,"elseCount":0},"{A=true, B=true, C=false, D=false, E=true}":{"thenCount":1,"elseCount":0},"{A=true, B=true, C=true, D=true, E=true}":{"thenCount":1,"elseCount":0}}}}}},{"region":{"regionID":"8dbd15aa-4d69-41b1-837b-203e98659719","startTime":-1,"endTime":-1,"duration":-1,"regionPackage":"edu.cmu.cs.mvelezce.analysis","regionClass":"ForExample","regionMethod":"main([Ljava/lang/String;)V","startRegionIndex":6,"startBlockID":"","endBlocksIDs":[],"startMethodBlock":null,"endMethodBlocks":[]},"info":{"stackTracesToContexts":{"[]":{"context":[["A"],["A","B"],["A","C"],["A","D"],["A","E"],["A","B","C"],["A","B","D"],["A","C","D"],["A","B","E"],["A","C","E"],["A","D","E"],["A","B","C","D"],["A","B","C","E"],["A","B","D","E"],["A","C","D","E"],["A","B","C","D","E"]]}},"stackTracesToDecisionBranchTables":{"[]":{"options":["A","B","C","D","E"],"table":{"{A=true, B=true, C=true, D=true, E=false}":{"thenCount":1,"elseCount":0},"{A=true, B=true, C=true, D=false, E=true}":{"thenCount":1,"elseCount":0},"{A=true, B=true, C=false, D=true, E=true}":{"thenCount":1,"elseCount":0},"{A=true, B=false, C=true, D=true, E=true}":{"thenCount":0,"elseCount":1},"{A=true, B=true, C=true, D=false, E=false}":{"thenCount":1,"elseCount":0},"{A=true, B=true, C=false, D=true, E=false}":{"thenCount":1,"elseCount":0},"{A=true, B=false, C=true, D=true, E=false}":{"thenCount":0,"elseCount":1},"{A=true, B=true, C=false, D=false, E=true}":{"thenCount":1,"elseCount":0},"{A=true, B=false, C=true, D=false, E=true}":{"thenCount":0,"elseCount":1},"{A=true, B=false, C=false, D=true, E=true}":{"thenCount":0,"elseCount":1},"{A=true, B=true, C=false, D=false, E=false}":{"thenCount":1,"elseCount":0},"{A=true, B=false, C=true, D=false, E=false}":{"thenCount":0,"elseCount":1},"{A=true, B=false, C=false, D=true, E=false}":{"thenCount":0,"elseCount":1},"{A=true, B=false, C=false, D=false, E=true}":{"thenCount":0,"elseCount":1},"{A=true, B=false, C=false, D=false, E=false}":{"thenCount":0,"elseCount":1},"{A=true, B=true, C=true, D=true, E=true}":{"thenCount":1,"elseCount":0}}}}}},{"region":{"regionID":"bc130325-1e1a-442f-aa62-18eb8def1fcd","startTime":-1,"endTime":-1,"duration":-1,"regionPackage":"edu.cmu.cs.mvelezce.analysis","regionClass":"ForExample","regionMethod":"main([Ljava/lang/String;)V","startRegionIndex":9,"startBlockID":"","endBlocksIDs":[],"startMethodBlock":null,"endMethodBlocks":[]},"info":{"stackTracesToContexts":{"[]":{"context":[[],["B"],["C"],["D"],["E"],["B","C"],["B","D"],["C","D"],["B","E"],["C","E"],["D","E"],["B","C","D"],["B","C","E"],["B","D","E"],["C","D","E"],["B","C","D","E"]]}},"stackTracesToDecisionBranchTables":{"[]":{"options":["A","B","C","D","E"],"table":{"{A=false, B=false, C=false, D=false, E=false}":{"thenCount":1,"elseCount":0},"{A=false, B=true, C=true, D=true, E=true}":{"thenCount":1,"elseCount":0},"{A=false, B=true, C=true, D=true, E=false}":{"thenCount":1,"elseCount":0},"{A=false, B=true, C=true, D=false, E=true}":{"thenCount":1,"elseCount":0},"{A=false, B=true, C=false, D=true, E=true}":{"thenCount":1,"elseCount":0},"{A=false, B=false, C=true, D=true, E=true}":{"thenCount":1,"elseCount":0},"{A=false, B=true, C=true, D=false, E=false}":{"thenCount":1,"elseCount":0},"{A=false, B=true, C=false, D=true, E=false}":{"thenCount":1,"elseCount":0},"{A=false, B=false, C=true, D=true, E=false}":{"thenCount":1,"elseCount":0},"{A=false, B=true, C=false, D=false, E=true}":{"thenCount":1,"elseCount":0},"{A=false, B=false, C=true, D=false, E=true}":{"thenCount":1,"elseCount":0},"{A=false, B=false, C=false, D=true, E=true}":{"thenCount":1,"elseCount":0},"{A=false, B=true, C=false, D=false, E=false}":{"thenCount":1,"elseCount":0},"{A=false, B=false, C=true, D=false, E=false}":{"thenCount":1,"elseCount":0},"{A=false, B=false, C=false, D=true, E=false}":{"thenCount":1,"elseCount":0},"{A=false, B=false, C=false, D=false, E=true}":{"thenCount":1,"elseCount":0}}}}}},{"region":{"regionID":"4ed531ca-3284-4bbe-a00e-d1f284f4a59b","startTime":-1,"endTime":-1,"duration":-1,"regionPackage":"edu.cmu.cs.mvelezce.analysis","regionClass":"ForExample","regionMethod":"main([Ljava/lang/String;)V","startRegionIndex":8,"startBlockID":"","endBlocksIDs":[],"startMethodBlock":null,"endMethodBlocks":[]},"info":{"stackTracesToContexts":{"[]":{"context":[["A"],["A","C"],["A","D"],["A","E"],["A","C","D"],["A","C","E"],["A","D","E"],["A","C","D","E"]]}},"stackTracesToDecisionBranchTables":{"[]":{"options":["A","B","C","D","E"],"table":{"{A=true, B=false, C=false, D=true, E=true}":{"thenCount":1,"elseCount":0},"{A=true, B=false, C=true, D=false, E=false}":{"thenCount":1,"elseCount":0},"{A=true, B=false, C=false, D=true, E=false}":{"thenCount":1,"elseCount":0},"{A=true, B=false, C=false, D=false, E=true}":{"thenCount":1,"elseCount":0},"{A=true, B=false, C=true, D=true, E=true}":{"thenCount":1,"elseCount":0},"{A=true, B=false, C=false, D=false, E=false}":{"thenCount":1,"elseCount":0},"{A=true, B=false, C=true, D=true, E=false}":{"thenCount":1,"elseCount":0},"{A=true, B=false, C=true, D=false, E=true}":{"thenCount":1,"elseCount":0}}}}}},{"region":{"regionID":"60fc5aa4-3773-4169-8b04-880e13049626","startTime":-1,"endTime":-1,"duration":-1,"regionPackage":"edu.cmu.cs.mvelezce.analysis","regionClass":"ForExample","regionMethod":"main([Ljava/lang/String;)V","startRegionIndex":3,"startBlockID":"","endBlocksIDs":[],"startMethodBlock":null,"endMethodBlocks":[]},"info":{"stackTracesToContexts":{"[]":{"context":[[],["A"],["B"],["C"],["A","B"],["D"],["A","C"],["E"],["B","C"],["A","D"],["B","D"],["A","E"],["A","B","C"],["C","D"],["B","E"],["A","B","D"],["C","E"],["A","C","D"],["A","B","E"],["D","E"],["B","C","D"],["A","C","E"],["B","C","E"],["A","D","E"],["A","B","C","D"],["B","D","E"],["A","B","C","E"],["C","D","E"],["A","B","D","E"],["A","C","D","E"],["B","C","D","E"],["A","B","C","D","E"]]}},"stackTracesToDecisionBranchTables":{"[]":{"options":["A","B","C","D","E"],"table":{"{A=true, B=true, C=true, D=true, E=false}":{"thenCount":4,"elseCount":1},"{A=true, B=true, C=true, D=false, E=true}":{"thenCount":4,"elseCount":1},"{A=false, B=true, C=true, D=true, E=true}":{"thenCount":1,"elseCount":1},"{A=true, B=true, C=false, D=true, E=true}":{"thenCount":4,"elseCount":1},"{A=true, B=false, C=true, D=true, E=true}":{"thenCount":4,"elseCount":1},"{A=true, B=true, C=true, D=false, E=false}":{"thenCount":4,"elseCount":1},"{A=false, B=true, C=true, D=true, E=false}":{"thenCount":1,"elseCount":1},"{A=false, B=true, C=true, D=false, E=true}":{"thenCount":1,"elseCount":1},"{A=true, B=true, C=false, D=true, E=false}":{"thenCount":4,"elseCount":1},"{A=true, B=false, C=true, D=true, E=false}":{"thenCount":4,"elseCount":1},"{A=true, B=true, C=false, D=false, E=true}":{"thenCount":4,"elseCount":1},"{A=true, B=false, C=true, D=false, E=true}":{"thenCount":4,"elseCount":1},"{A=false, B=true, C=false, D=true, E=true}":{"thenCount":1,"elseCount":1},"{A=false, B=false, C=true, D=true, E=true}":{"thenCount":1,"elseCount":1},"{A=false, B=true, C=true, D=false, E=false}":{"thenCount":1,"elseCount":1},"{A=true, B=false, C=false, D=true, E=true}":{"thenCount":4,"elseCount":1},"{A=true, B=true, C=false, D=false, E=false}":{"thenCount":4,"elseCount":1},"{A=true, B=false, C=true, D=false, E=false}":{"thenCount":4,"elseCount":1},"{A=false, B=true, C=false, D=true, E=false}":{"thenCount":1,"elseCount":1},"{A=false, B=false, C=true, D=true, E=false}":{"thenCount":1,"elseCount":1},"{A=false, B=true, C=false, D=false, E=true}":{"thenCount":1,"elseCount":1},"{A=false, B=false, C=true, D=false, E=true}":{"thenCount":1,"elseCount":1},"{A=true, B=false, C=false, D=true, E=false}":{"thenCount":4,"elseCount":1},"{A=true, B=false, C=false, D=false, E=true}":{"thenCount":4,"elseCount":1},"{A=false, B=false, C=false, D=true, E=true}":{"thenCount":1,"elseCount":1},"{A=false, B=true, C=false, D=false, E=false}":{"thenCount":1,"elseCount":1},"{A=false, B=false, C=true, D=false, E=false}":{"thenCount":1,"elseCount":1},"{A=true, B=false, C=false, D=false, E=false}":{"thenCount":4,"elseCount":1},"{A=false, B=false, C=false, D=true, E=false}":{"thenCount":1,"elseCount":1},"{A=false, B=false, C=false, D=false, E=true}":{"thenCount":1,"elseCount":1},"{A=false, B=false, C=false, D=false, E=false}":{"thenCount":1,"elseCount":1},"{A=true, B=true, C=true, D=true, E=true}":{"thenCount":4,"elseCount":1}}}}}},{"region":{"regionID":"0d49add7-0bf7-4ba4-9ca3-7969bf4b9a58","startTime":-1,"endTime":-1,"duration":-1,"regionPackage":"edu.cmu.cs.mvelezce.analysis","regionClass":"ForExample","regionMethod":"main([Ljava/lang/String;)V","startRegionIndex":2,"startBlockID":"","endBlocksIDs":[],"startMethodBlock":null,"endMethodBlocks":[]},"info":{"stackTracesToContexts":{"[]":{"context":[[],["A"],["B"],["C"],["A","B"],["D"],["A","C"],["E"],["B","C"],["A","D"],["B","D"],["A","E"],["A","B","C"],["C","D"],["B","E"],["A","B","D"],["C","E"],["A","C","D"],["A","B","E"],["D","E"],["B","C","D"],["A","C","E"],["B","C","E"],["A","D","E"],["A","B","C","D"],["B","D","E"],["A","B","C","E"],["C","D","E"],["A","B","D","E"],["A","C","D","E"],["B","C","D","E"],["A","B","C","D","E"]]}},"stackTracesToDecisionBranchTables":{"[]":{"options":["A","B","C","D","E"],"table":{"{A=true, B=true, C=true, D=true, E=false}":{"thenCount":1,"elseCount":0},"{A=true, B=true, C=true, D=false, E=true}":{"thenCount":1,"elseCount":0},"{A=false, B=true, C=true, D=true, E=true}":{"thenCount":1,"elseCount":0},"{A=true, B=true, C=false, D=true, E=true}":{"thenCount":1,"elseCount":0},"{A=true, B=false, C=true, D=true, E=true}":{"thenCount":0,"elseCount":1},"{A=true, B=true, C=true, D=false, E=false}":{"thenCount":1,"elseCount":0},"{A=false, B=true, C=true, D=true, E=false}":{"thenCount":1,"elseCount":0},"{A=false, B=true, C=true, D=false, E=true}":{"thenCount":1,"elseCount":0},"{A=true, B=true, C=false, D=true, E=false}":{"thenCount":1,"elseCount":0},"{A=true, B=false, C=true, D=true, E=false}":{"thenCount":0,"elseCount":1},"{A=true, B=true, C=false, D=false, E=true}":{"thenCount":1,"elseCount":0},"{A=true, B=false, C=true, D=false, E=true}":{"thenCount":0,"elseCount":1},"{A=false, B=true, C=false, D=true, E=true}":{"thenCount":1,"elseCount":0},"{A=false, B=false, C=true, D=true, E=true}":{"thenCount":0,"elseCount":1},"{A=false, B=true, C=true, D=false, E=false}":{"thenCount":1,"elseCount":0},"{A=true, B=false, C=false, D=true, E=true}":{"thenCount":0,"elseCount":1},"{A=true, B=true, C=false, D=false, E=false}":{"thenCount":1,"elseCount":0},"{A=true, B=false, C=true, D=false, E=false}":{"thenCount":0,"elseCount":1},"{A=false, B=true, C=false, D=true, E=false}":{"thenCount":1,"elseCount":0},"{A=false, B=false, C=true, D=true, E=false}":{"thenCount":0,"elseCount":1},"{A=false, B=true, C=false, D=false, E=true}":{"thenCount":1,"elseCount":0},"{A=false, B=false, C=true, D=false, E=true}":{"thenCount":0,"elseCount":1},"{A=true, B=false, C=false, D=true, E=false}":{"thenCount":0,"elseCount":1},"{A=true, B=false, C=false, D=false, E=true}":{"thenCount":0,"elseCount":1},"{A=false, B=false, C=false, D=true, E=true}":{"thenCount":0,"elseCount":1},"{A=false, B=true, C=false, D=false, E=false}":{"thenCount":1,"elseCount":0},"{A=false, B=false, C=true, D=false, E=false}":{"thenCount":0,"elseCount":1},"{A=true, B=false, C=false, D=false, E=false}":{"thenCount":0,"elseCount":1},"{A=false, B=false, C=false, D=true, E=false}":{"thenCount":0,"elseCount":1},"{A=false, B=false, C=false, D=false, E=true}":{"thenCount":0,"elseCount":1},"{A=false, B=false, C=false, D=false, E=false}":{"thenCount":0,"elseCount":1},"{A=true, B=true, C=true, D=true, E=true}":{"thenCount":1,"elseCount":0}}}}}},{"region":{"regionID":"7ce6634b-5ff0-47da-9e13-74d2aee9e5c6","startTime":-1,"endTime":-1,"duration":-1,"regionPackage":"edu.cmu.cs.mvelezce.analysis","regionClass":"ForExample","regionMethod":"main([Ljava/lang/String;)V","startRegionIndex":5,"startBlockID":"","endBlocksIDs":[],"startMethodBlock":null,"endMethodBlocks":[]},"info":{"stackTracesToContexts":{"[]":{"context":[["A"],["A","B"],["A","C"],["A","D"],["A","E"],["A","B","C"],["A","B","D"],["A","C","D"],["A","B","E"],["A","C","E"],["A","D","E"],["A","B","C","D"],["A","B","C","E"],["A","B","D","E"],["A","C","D","E"],["A","B","C","D","E"]]}},"stackTracesToDecisionBranchTables":{"[]":{"options":["A","B","C","D","E"],"table":{"{A=true, B=true, C=true, D=true, E=false}":{"thenCount":1,"elseCount":0},"{A=true, B=true, C=true, D=false, E=true}":{"thenCount":1,"elseCount":0},"{A=true, B=true, C=false, D=true, E=true}":{"thenCount":1,"elseCount":0},"{A=true, B=false, C=true, D=true, E=true}":{"thenCount":1,"elseCount":0},"{A=true, B=true, C=true, D=false, E=false}":{"thenCount":1,"elseCount":0},"{A=true, B=true, C=false, D=true, E=false}":{"thenCount":1,"elseCount":0},"{A=true, B=false, C=true, D=true, E=false}":{"thenCount":1,"elseCount":0},"{A=true, B=true, C=false, D=false, E=true}":{"thenCount":1,"elseCount":0},"{A=true, B=false, C=true, D=false, E=true}":{"thenCount":1,"elseCount":0},"{A=true, B=false, C=false, D=true, E=true}":{"thenCount":1,"elseCount":0},"{A=true, B=true, C=false, D=false, E=false}":{"thenCount":1,"elseCount":0},"{A=true, B=false, C=true, D=false, E=false}":{"thenCount":1,"elseCount":0},"{A=true, B=false, C=false, D=true, E=false}":{"thenCount":1,"elseCount":0},"{A=true, B=false, C=false, D=false, E=true}":{"thenCount":1,"elseCount":0},"{A=true, B=false, C=false, D=false, E=false}":{"thenCount":1,"elseCount":0},"{A=true, B=true, C=true, D=true, E=true}":{"thenCount":1,"elseCount":0}}}}}},{"region":{"regionID":"b53a268a-a594-4e8d-a611-90359c8f921e","startTime":-1,"endTime":-1,"duration":-1,"regionPackage":"edu.cmu.cs.mvelezce.analysis","regionClass":"ForExample","regionMethod":"main([Ljava/lang/String;)V","startRegionIndex":4,"startBlockID":"","endBlocksIDs":[],"startMethodBlock":null,"endMethodBlocks":[]},"info":{"stackTracesToContexts":{"[]":{"context":[[],["A"],["B"],["C"],["A","B"],["D"],["A","C"],["E"],["B","C"],["A","D"],["B","D"],["A","E"],["A","B","C"],["C","D"],["B","E"],["A","B","D"],["C","E"],["A","C","D"],["A","B","E"],["D","E"],["B","C","D"],["A","C","E"],["B","C","E"],["A","D","E"],["A","B","C","D"],["B","D","E"],["A","B","C","E"],["C","D","E"],["A","B","D","E"],["A","C","D","E"],["B","C","D","E"],["A","B","C","D","E"]]}},"stackTracesToDecisionBranchTables":{"[]":{"options":["A","B","C","D","E"],"table":{"{A=true, B=true, C=true, D=true, E=false}":{"thenCount":1,"elseCount":0},"{A=true, B=true, C=true, D=false, E=true}":{"thenCount":1,"elseCount":0},"{A=false, B=true, C=true, D=true, E=true}":{"thenCount":0,"elseCount":1},"{A=true, B=true, C=false, D=true, E=true}":{"thenCount":1,"elseCount":0},"{A=true, B=false, C=true, D=true, E=true}":{"thenCount":1,"elseCount":0},"{A=true, B=true, C=true, D=false, E=false}":{"thenCount":1,"elseCount":0},"{A=false, B=true, C=true, D=true, E=false}":{"thenCount":0,"elseCount":1},"{A=false, B=true, C=true, D=false, E=true}":{"thenCount":0,"elseCount":1},"{A=true, B=true, C=false, D=true, E=false}":{"thenCount":1,"elseCount":0},"{A=true, B=false, C=true, D=true, E=false}":{"thenCount":1,"elseCount":0},"{A=true, B=true, C=false, D=false, E=true}":{"thenCount":1,"elseCount":0},"{A=true, B=false, C=true, D=false, E=true}":{"thenCount":1,"elseCount":0},"{A=false, B=true, C=false, D=true, E=true}":{"thenCount":0,"elseCount":1},"{A=false, B=false, C=true, D=true, E=true}":{"thenCount":0,"elseCount":1},"{A=false, B=true, C=true, D=false, E=false}":{"thenCount":0,"elseCount":1},"{A=true, B=false, C=false, D=true, E=true}":{"thenCount":1,"elseCount":0},"{A=true, B=true, C=false, D=false, E=false}":{"thenCount":1,"elseCount":0},"{A=true, B=false, C=true, D=false, E=false}":{"thenCount":1,"elseCount":0},"{A=false, B=true, C=false, D=true, E=false}":{"thenCount":0,"elseCount":1},"{A=false, B=false, C=true, D=true, E=false}":{"thenCount":0,"elseCount":1},"{A=false, B=true, C=false, D=false, E=true}":{"thenCount":0,"elseCount":1},"{A=false, B=false, C=true, D=false, E=true}":{"thenCount":0,"elseCount":1},"{A=true, B=false, C=false, D=true, E=false}":{"thenCount":1,"elseCount":0},"{A=true, B=false, C=false, D=false, E=true}":{"thenCount":1,"elseCount":0},"{A=false, B=false, C=false, D=true, E=true}":{"thenCount":0,"elseCount":1},"{A=false, B=true, C=false, D=false, E=false}":{"thenCount":0,"elseCount":1},"{A=false, B=false, C=true, D=false, E=false}":{"thenCount":0,"elseCount":1},"{A=true, B=false, C=false, D=false, E=false}":{"thenCount":1,"elseCount":0},"{A=false, B=false, C=false, D=true, E=false}":{"thenCount":0,"elseCount":1},"{A=false, B=false, C=false, D=false, E=true}":{"thenCount":0,"elseCount":1},"{A=false, B=false, C=false, D=false, E=false}":{"thenCount":0,"elseCount":1},"{A=true, B=true, C=true, D=true, E=true}":{"thenCount":1,"elseCount":0}}}}}},{"region":{"regionID":"6321b114-e341-4145-b321-f4c117112d59","startTime":-1,"endTime":-1,"duration":-1,"regionPackage":"edu.cmu.cs.mvelezce.analysis","regionClass":"ForExample","regionMethod":"main([Ljava/lang/String;)V","startRegionIndex":1,"startBlockID":"","endBlocksIDs":[],"startMethodBlock":null,"endMethodBlocks":[]},"info":{"stackTracesToContexts":{"[]":{"context":[[],["A"],["B"],["C"],["A","B"],["D"],["A","C"],["E"],["B","C"],["A","D"],["B","D"],["A","E"],["A","B","C"],["C","D"],["B","E"],["A","B","D"],["C","E"],["A","C","D"],["A","B","E"],["D","E"],["B","C","D"],["A","C","E"],["B","C","E"],["A","D","E"],["A","B","C","D"],["B","D","E"],["A","B","C","E"],["C","D","E"],["A","B","D","E"],["A","C","D","E"],["B","C","D","E"],["A","B","C","D","E"]]}},"stackTracesToDecisionBranchTables":{"[]":{"options":["A","B","C","D","E"],"table":{"{A=true, B=true, C=true, D=true, E=false}":{"thenCount":1,"elseCount":0},"{A=true, B=true, C=true, D=false, E=true}":{"thenCount":1,"elseCount":0},"{A=false, B=true, C=true, D=true, E=true}":{"thenCount":0,"elseCount":1},"{A=true, B=true, C=false, D=true, E=true}":{"thenCount":1,"elseCount":0},"{A=true, B=false, C=true, D=true, E=true}":{"thenCount":1,"elseCount":0},"{A=true, B=true, C=true, D=false, E=false}":{"thenCount":1,"elseCount":0},"{A=false, B=true, C=true, D=true, E=false}":{"thenCount":0,"elseCount":1},"{A=false, B=true, C=true, D=false, E=true}":{"thenCount":0,"elseCount":1},"{A=true, B=true, C=false, D=true, E=false}":{"thenCount":1,"elseCount":0},"{A=true, B=false, C=true, D=true, E=false}":{"thenCount":1,"elseCount":0},"{A=true, B=true, C=false, D=false, E=true}":{"thenCount":1,"elseCount":0},"{A=true, B=false, C=true, D=false, E=true}":{"thenCount":1,"elseCount":0},"{A=false, B=true, C=false, D=true, E=true}":{"thenCount":0,"elseCount":1},"{A=false, B=false, C=true, D=true, E=true}":{"thenCount":0,"elseCount":1},"{A=false, B=true, C=true, D=false, E=false}":{"thenCount":0,"elseCount":1},"{A=true, B=false, C=false, D=true, E=true}":{"thenCount":1,"elseCount":0},"{A=true, B=true, C=false, D=false, E=false}":{"thenCount":1,"elseCount":0},"{A=true, B=false, C=true, D=false, E=false}":{"thenCount":1,"elseCount":0},"{A=false, B=true, C=false, D=true, E=false}":{"thenCount":0,"elseCount":1},"{A=false, B=false, C=true, D=true, E=false}":{"thenCount":0,"elseCount":1},"{A=false, B=true, C=false, D=false, E=true}":{"thenCount":0,"elseCount":1},"{A=false, B=false, C=true, D=false, E=true}":{"thenCount":0,"elseCount":1},"{A=true, B=false, C=false, D=true, E=false}":{"thenCount":1,"elseCount":0},"{A=true, B=false, C=false, D=false, E=true}":{"thenCount":1,"elseCount":0},"{A=false, B=false, C=false, D=true, E=true}":{"thenCount":0,"elseCount":1},"{A=false, B=true, C=false, D=false, E=false}":{"thenCount":0,"elseCount":1},"{A=false, B=false, C=true, D=false, E=false}":{"thenCount":0,"elseCount":1},"{A=true, B=false, C=false, D=false, E=false}":{"thenCount":1,"elseCount":0},"{A=false, B=false, C=false, D=true, E=false}":{"thenCount":0,"elseCount":1},"{A=false, B=false, C=false, D=false, E=true}":{"thenCount":0,"elseCount":1},"{A=false, B=false, C=false, D=false, E=false}":{"thenCount":0,"elseCount":1},"{A=true, B=true, C=true, D=true, E=true}":{"thenCount":1,"elseCount":0}}}}}},{"region":{"regionID":"7e388ee4-1846-4919-81e6-4320b602edc5","startTime":-1,"endTime":-1,"duration":-1,"regionPackage":"edu.cmu.cs.mvelezce.analysis","regionClass":"ForExample","regionMethod":"main([Ljava/lang/String;)V","startRegionIndex":11,"startBlockID":"","endBlocksIDs":[],"startMethodBlock":null,"endMethodBlocks":[]},"info":{"stackTracesToContexts":{"[]":{"context":[["B"],["B","C"],["B","D"],["B","E"],["B","C","D"],["B","C","E"],["B","D","E"],["B","C","D","E"]]}},"stackTracesToDecisionBranchTables":{"[]":{"options":["A","B","C","D","E"],"table":{"{A=false, B=true, C=false, D=true, E=false}":{"thenCount":1,"elseCount":0},"{A=false, B=true, C=false, D=false, E=true}":{"thenCount":1,"elseCount":0},"{A=false, B=true, C=true, D=true, E=true}":{"thenCount":1,"elseCount":0},"{A=false, B=true, C=false, D=false, E=false}":{"thenCount":1,"elseCount":0},"{A=false, B=true, C=true, D=true, E=false}":{"thenCount":1,"elseCount":0},"{A=false, B=true, C=true, D=false, E=true}":{"thenCount":1,"elseCount":0},"{A=false, B=true, C=false, D=true, E=true}":{"thenCount":1,"elseCount":0},"{A=false, B=true, C=true, D=false, E=false}":{"thenCount":1,"elseCount":0}}}}}},{"region":{"regionID":"90bedb1b-df9a-4d5d-9a43-fcfaaf6e8faf","startTime":-1,"endTime":-1,"duration":-1,"regionPackage":"edu.cmu.cs.mvelezce.analysis","regionClass":"ForExample","regionMethod":"main([Ljava/lang/String;)V","startRegionIndex":10,"startBlockID":"","endBlocksIDs":[],"startMethodBlock":null,"endMethodBlocks":[]},"info":{"stackTracesToContexts":{"[]":{"context":[[],["B"],["C"],["D"],["E"],["B","C"],["B","D"],["C","D"],["B","E"],["C","E"],["D","E"],["B","C","D"],["B","C","E"],["B","D","E"],["C","D","E"],["B","C","D","E"]]}},"stackTracesToDecisionBranchTables":{"[]":{"options":["A","B","C","D","E"],"table":{"{A=false, B=false, C=false, D=false, E=false}":{"thenCount":0,"elseCount":1},"{A=false, B=true, C=true, D=true, E=true}":{"thenCount":1,"elseCount":0},"{A=false, B=true, C=true, D=true, E=false}":{"thenCount":1,"elseCount":0},"{A=false, B=true, C=true, D=false, E=true}":{"thenCount":1,"elseCount":0},"{A=false, B=true, C=false, D=true, E=true}":{"thenCount":1,"elseCount":0},"{A=false, B=false, C=true, D=true, E=true}":{"thenCount":0,"elseCount":1},"{A=false, B=true, C=true, D=false, E=false}":{"thenCount":1,"elseCount":0},"{A=false, B=true, C=false, D=true, E=false}":{"thenCount":1,"elseCount":0},"{A=false, B=false, C=true, D=true, E=false}":{"thenCount":0,"elseCount":1},"{A=false, B=true, C=false, D=false, E=true}":{"thenCount":1,"elseCount":0},"{A=false, B=false, C=true, D=false, E=true}":{"thenCount":0,"elseCount":1},"{A=false, B=false, C=false, D=true, E=true}":{"thenCount":0,"elseCount":1},"{A=false, B=true, C=false, D=false, E=false}":{"thenCount":1,"elseCount":0},"{A=false, B=false, C=true, D=false, E=false}":{"thenCount":0,"elseCount":1},"{A=false, B=false, C=false, D=true, E=false}":{"thenCount":0,"elseCount":1},"{A=false, B=false, C=false, D=false, E=true}":{"thenCount":0,"elseCount":1}}}}}},{"region":{"regionID":"ed2e3032-db71-4f1b-873a-ff8a24af4616","startTime":-1,"endTime":-1,"duration":-1,"regionPackage":"edu.cmu.cs.mvelezce.analysis","regionClass":"ForExample","regionMethod":"main([Ljava/lang/String;)V","startRegionIndex":12,"startBlockID":"","endBlocksIDs":[],"startMethodBlock":null,"endMethodBlocks":[]},"info":{"stackTracesToContexts":{"[]":{"context":[[],["C"],["D"],["E"],["C","D"],["C","E"],["D","E"],["C","D","E"]]}},"stackTracesToDecisionBranchTables":{"[]":{"options":["A","B","C","D","E"],"table":{"{A=false, B=false, C=false, D=false, E=false}":{"thenCount":1,"elseCount":0},"{A=false, B=false, C=true, D=true, E=false}":{"thenCount":1,"elseCount":0},"{A=false, B=false, C=true, D=false, E=true}":{"thenCount":1,"elseCount":0},"{A=false, B=false, C=false, D=true, E=true}":{"thenCount":1,"elseCount":0},"{A=false, B=false, C=true, D=false, E=false}":{"thenCount":1,"elseCount":0},"{A=false, B=false, C=false, D=true, E=false}":{"thenCount":1,"elseCount":0},"{A=false, B=false, C=false, D=false, E=true}":{"thenCount":1,"elseCount":0},"{A=false, B=false, C=true, D=true, E=true}":{"thenCount":1,"elseCount":0}}}}}}]