{"region":"0a567ad9-1498-43f0-95ff-1701684f5439","model":{"(!MAX_MEMORY && REPLICATED)":0.0,"(MAX_MEMORY && REPLICATED)":0.0,"(MAX_MEMORY && !REPLICATED)":0.0,"(!MAX_MEMORY && !REPLICATED)":0.0},"modelToMin":{"(!MAX_MEMORY && REPLICATED)":0.0,"(MAX_MEMORY && REPLICATED)":0.0,"(MAX_MEMORY && !REPLICATED)":0.0,"(!MAX_MEMORY && !REPLICATED)":0.0},"modelToMax":{"(!MAX_MEMORY && REPLICATED)":0.0,"(MAX_MEMORY && REPLICATED)":0.0,"(MAX_MEMORY && !REPLICATED)":5312000.0,"(!MAX_MEMORY && !REPLICATED)":5367000.0},"modelToDiff":{"(!MAX_MEMORY && REPLICATED)":0.0,"(MAX_MEMORY && REPLICATED)":0.0,"(MAX_MEMORY && !REPLICATED)":5312000.0,"(!MAX_MEMORY && !REPLICATED)":5367000.0},"modelToSampleVariance":{"(!MAX_MEMORY && REPLICATED)":0.0,"(MAX_MEMORY && REPLICATED)":0.0,"(MAX_MEMORY && !REPLICATED)":2.992023192394653E12,"(!MAX_MEMORY && !REPLICATED)":1.602786693814624E12},"modelToConfidenceInterval":{"(!MAX_MEMORY && REPLICATED)":[],"(MAX_MEMORY && REPLICATED)":[],"(MAX_MEMORY && !REPLICATED)":[351713.00299935974,929801.2827149257],"(!MAX_MEMORY && !REPLICATED)":[114951.0054098856,524861.075127027]},"modelToPerfHumanReadable":{"(!MAX_MEMORY && REPLICATED)":"0.0000000","(MAX_MEMORY && REPLICATED)":"0.0000000","(MAX_MEMORY && !REPLICATED)":"0.0000000","(!MAX_MEMORY && !REPLICATED)":"0.0000000"},"modelToMinHumanReadable":{"(!MAX_MEMORY && REPLICATED)":"0.0000000","(MAX_MEMORY && REPLICATED)":"0.0000000","(MAX_MEMORY && !REPLICATED)":"0.0000000","(!MAX_MEMORY && !REPLICATED)":"0.0000000"},"modelToMaxHumanReadable":{"(!MAX_MEMORY && REPLICATED)":"0.0000000","(MAX_MEMORY && REPLICATED)":"0.0000000","(MAX_MEMORY && !REPLICATED)":"0.0053120","(!MAX_MEMORY && !REPLICATED)":"0.0053670"},"modelToDiffHumanReadable":{"(!MAX_MEMORY && REPLICATED)":"0.0000000","(MAX_MEMORY && REPLICATED)":"0.0000000","(MAX_MEMORY && !REPLICATED)":"0.0053120","(!MAX_MEMORY && !REPLICATED)":"0.0053670"},"modelToSampleVarianceHumanReadble":{"(!MAX_MEMORY && REPLICATED)":"0.0000000","(MAX_MEMORY && REPLICATED)":"0.0000000","(MAX_MEMORY && !REPLICATED)":"0.0000030","(!MAX_MEMORY && !REPLICATED)":"0.0000016"},"modelToConfidenceIntervalHumanReadable":{"(!MAX_MEMORY && REPLICATED)":[],"(MAX_MEMORY && REPLICATED)":[],"(MAX_MEMORY && !REPLICATED)":["0.0003517","0.0009298"],"(!MAX_MEMORY && !REPLICATED)":["0.0001150","0.0005249"]}}