[{"region":{"regionID":"6552fc17-4746-47af-ac9c-f2eaa2592955","startTime":-1,"endTime":-1,"duration":-1,"regionPackage":"edu.cmu.cs.mvelezce","regionClass":"Regions20","regionMethod":"moo(ZZZ)V","startBytecodeIndex":13,"startMethodBlock":null,"endMethodBlocks":[]},"options":[["A","B"]]},{"region":{"regionID":"49a1a900-cbe5-4263-baa3-1b4330b3f834","startTime":-1,"endTime":-1,"duration":-1,"regionPackage":"edu.cmu.cs.mvelezce","regionClass":"Regions20","regionMethod":"moo(ZZZ)V","startBytecodeIndex":15,"startMethodBlock":null,"endMethodBlocks":[]},"options":[["A","B"]]},{"region":{"regionID":"fb5096ec-7a25-47cd-b37c-3b82257fc9ce","startTime":-1,"endTime":-1,"duration":-1,"regionPackage":"edu.cmu.cs.mvelezce","regionClass":"Regions20","regionMethod":"bar(ZZ)V","startBytecodeIndex":14,"startMethodBlock":null,"endMethodBlocks":[]},"options":[["A","C"]]},{"region":{"regionID":"9283a22a-1487-4b6a-bb74-736dff27d4ac","startTime":-1,"endTime":-1,"duration":-1,"regionPackage":"edu.cmu.cs.mvelezce","regionClass":"Regions20","regionMethod":"main([Ljava/lang/String;)V","startBytecodeIndex":63,"startMethodBlock":null,"endMethodBlocks":[]},"options":[["C"]]},{"region":{"regionID":"c600bc3e-042a-4189-bcab-fe552ff20d06","startTime":-1,"endTime":-1,"duration":-1,"regionPackage":"edu.cmu.cs.mvelezce","regionClass":"Regions20","regionMethod":"bar(ZZ)V","startBytecodeIndex":12,"startMethodBlock":null,"endMethodBlocks":[]},"options":[["A","C"]]},{"region":{"regionID":"8b34a112-e137-4117-9f9e-206c5a92bce9","startTime":-1,"endTime":-1,"duration":-1,"regionPackage":"edu.cmu.cs.mvelezce","regionClass":"Regions20","regionMethod":"foo(ZZZ)V","startBytecodeIndex":3,"startMethodBlock":null,"endMethodBlocks":[]},"options":[["A"]]},{"region":{"regionID":"ceca48e8-89fd-438d-bbe0-57b8de854495","startTime":-1,"endTime":-1,"duration":-1,"regionPackage":"edu.cmu.cs.mvelezce","regionClass":"Regions20","regionMethod":"main([Ljava/lang/String;)V","startBytecodeIndex":63,"startMethodBlock":null,"endMethodBlocks":[]},"options":[["C"]]},{"region":{"regionID":"c68df5df-7721-4ba8-98d3-f918a1124552","startTime":-1,"endTime":-1,"duration":-1,"regionPackage":"edu.cmu.cs.mvelezce","regionClass":"Regions20","regionMethod":"bar(ZZ)V","startBytecodeIndex":0,"startMethodBlock":null,"endMethodBlocks":[]},"options":[["A","C"]]},{"region":{"regionID":"358e70a3-2699-44f5-a9dd-b4e86fa3df8e","startTime":-1,"endTime":-1,"duration":-1,"regionPackage":"edu.cmu.cs.mvelezce","regionClass":"Regions20","regionMethod":"main([Ljava/lang/String;)V","startBytecodeIndex":54,"startMethodBlock":null,"endMethodBlocks":[]},"options":[["B"]]},{"region":{"regionID":"1c411941-5931-4378-858c-e0036ebc2e99","startTime":-1,"endTime":-1,"duration":-1,"regionPackage":"edu.cmu.cs.mvelezce","regionClass":"Regions20","regionMethod":"moo(ZZZ)V","startBytecodeIndex":3,"startMethodBlock":null,"endMethodBlocks":[]},"options":[["A","B"]]},{"region":{"regionID":"78f5edb5-5ec4-4bb8-a447-83aae13c51a0","startTime":-1,"endTime":-1,"duration":-1,"regionPackage":"edu.cmu.cs.mvelezce","regionClass":"Regions20","regionMethod":"moo(ZZZ)V","startBytecodeIndex":0,"startMethodBlock":null,"endMethodBlocks":[]},"options":[["A","B"]]},{"region":{"regionID":"592840da-e812-4c5d-8861-e7c04dac0ca1","startTime":-1,"endTime":-1,"duration":-1,"regionPackage":"edu.cmu.cs.mvelezce","regionClass":"Regions20","regionMethod":"main([Ljava/lang/String;)V","startBytecodeIndex":45,"startMethodBlock":null,"endMethodBlocks":[]},"options":[["A"]]},{"region":{"regionID":"5c5e94d6-abf9-4f10-bd7c-2b03302ba178","startTime":-1,"endTime":-1,"duration":-1,"regionPackage":"edu.cmu.cs.mvelezce","regionClass":"Regions20","regionMethod":"moo(ZZZ)V","startBytecodeIndex":3,"startMethodBlock":null,"endMethodBlocks":[]},"options":[["A","B"]]},{"region":{"regionID":"96c99ce5-ec65-4180-9c62-670ec91e0eeb","startTime":-1,"endTime":-1,"duration":-1,"regionPackage":"edu.cmu.cs.mvelezce","regionClass":"Regions20","regionMethod":"main([Ljava/lang/String;)V","startBytecodeIndex":54,"startMethodBlock":null,"endMethodBlocks":[]},"options":[["B"]]},{"region":{"regionID":"6be70d59-9806-431d-add9-4f4a4daa2919","startTime":-1,"endTime":-1,"duration":-1,"regionPackage":"edu.cmu.cs.mvelezce","regionClass":"Regions20","regionMethod":"main([Ljava/lang/String;)V","startBytecodeIndex":45,"startMethodBlock":null,"endMethodBlocks":[]},"options":[["A"]]},{"region":{"regionID":"81e1eacf-7476-4820-8c02-2ee866a9f0a8","startTime":-1,"endTime":-1,"duration":-1,"regionPackage":"edu.cmu.cs.mvelezce","regionClass":"Regions20","regionMethod":"bar(ZZ)V","startBytecodeIndex":3,"startMethodBlock":null,"endMethodBlocks":[]},"options":[["A","C"]]},{"region":{"regionID":"59624555-c928-470c-adac-09bbec6179ea","startTime":-1,"endTime":-1,"duration":-1,"regionPackage":"edu.cmu.cs.mvelezce","regionClass":"Regions20","regionMethod":"bar(ZZ)V","startBytecodeIndex":3,"startMethodBlock":null,"endMethodBlocks":[]},"options":[["A","C"]]},{"region":{"regionID":"cb997d6c-ffec-4e0d-9d8e-bc439f4567f1","startTime":-1,"endTime":-1,"duration":-1,"regionPackage":"edu.cmu.cs.mvelezce","regionClass":"Regions20","regionMethod":"foo(ZZZ)V","startBytecodeIndex":3,"startMethodBlock":null,"endMethodBlocks":[]},"options":[["A"]]}]